ghiblify/__init__.py
ghiblify-0.0.1.dist-info/METADATA
ghiblify-0.0.1.dist-info/WHEEL
ghiblify-0.0.1.dist-info/top_level.txt
ghiblify-0.0.1.dist-info/RECORD
