Metadata-Version: 2.4
Name: ghiblify
Version: 0.0.1
Summary: Ghiblifies your images
Author-email: cblagden <chase.blagden@gmail.com>
